MANIFEST.in
README.md
requirements.txt
secure_cert_mfg.py
setup.py
esp_cryptoauth_utility.egg-info/PKG-INFO
esp_cryptoauth_utility.egg-info/SOURCES.txt
esp_cryptoauth_utility.egg-info/dependency_links.txt
esp_cryptoauth_utility.egg-info/requires.txt
esp_cryptoauth_utility.egg-info/top_level.txt
helper_scripts/__init__.py
helper_scripts/cert2certdef.py
helper_scripts/cert_sign.py
helper_scripts/manifest.py
helper_scripts/serial.py
sample_bins/READMe.md
sample_bins/__init__.py
sample_bins/secure_cert_mfg.bin
sample_bins/esp32/info.txt
sample_bins/esp32/secure_cert_mfg_esp32.bin
sample_bins/esp32c2/info.txt
sample_bins/esp32c2/secure_cert_mfg_esp32c2.bin
sample_bins/esp32c3/info.txt
sample_bins/esp32c3/secure_cert_mfg_esp32c3.bin
sample_bins/esp32c6/info.txt
sample_bins/esp32c6/secure_cert_mfg_esp32c6.bin
sample_bins/esp32h2/info.txt
sample_bins/esp32h2/secure_cert_mfg_esp32h2.bin
sample_bins/esp32p4/info.txt
sample_bins/esp32p4/secure_cert_mfg_esp32p4.bin
sample_bins/esp32s3/info.txt
sample_bins/esp32s3/secure_cert_mfg_esp32s3.bin
sample_certs/__init__.py
sample_certs/sample_signer_cert.pem
sample_certs/sample_signer_key.pem